Workbook

Sheet Параметры
A1: ПАРАМЕТРЫ МОДЕЛИ ЦПИКП v3
A3: --- Общие параметры ---
A4: Горизонт, лет | B4: 10
A5: Ставка дисконтирования (r) | B5: 0.12 | C5: Проектная: ОФЗ-10Y + 2%
A6: Страховые взносы | B6: 0.302 | C6: 30,2%
A7: Индексация OPEX, %/год | B7: 0.05 | C7: +5% ежегодно
A8: OPEX Год 1, тыс. | B8: 28200 | C8: Источник: Реестр Решений №8
A10: --- Штат по фазам ---
A11: Штат Фаза 1 (Год 1-2) | B11: 25
A12: Штат Фаза 2 (Год 3-5) | B12: 32 | C12: +7 чел.
A13: Штат Фаза 3 (Год 6-10) | B13: 35 | C13: +3 чел.
A15: --- Множители переменной ---
A16: Множитель Год 1 (80/20) | B16: 0.25 | C16: Перем. = Фикс × 0,25
A17: Множитель Год 2 (60/40) | B17: 0.67 | C17: Перем. = Фикс × 0,67
A18: Множитель Год 3+ (40/60) | B18: 1.5 | C18: Перем. = Фикс × 1,50
A20: --- Ставки Cash-in (BASE) ---
A21: Группа А (Росатом, ДПО, гранты) | B21: 0.6 | C21: Консервативная оценка
A22: Группа Б (НИОКР, лицензирование) | B22: 0.45
A23: Группа В (фандрайзинг, спин-оффы) | B23: 0.2
A25: --- Ставки Cash-in (SENSITIVITY) ---
A26: Группа А (sensitivity) | B26: 0.75 | C26: Из Реестра Решений
A27: Группа Б (sensitivity) | B27: 0.5
A28: Группа В (sensitivity) | B28: 0.25
A30: --- Сценарные коэффициенты ---
A31: Пессимистичный (×TCV) | B31: 0.7
A32: Оптимистичный (×TCV) | B32: 1.37
A33: Санкционный стресс (×TCV) | B33: 0.85
A35: --- Baseline (Net New) ---
A36: Baseline TCV, млн/год | B36: 500 | C36: Текущий уровень без ЦПИКП
A38: --- NPV sensitivity ставки ---
A39: r low | B39: 0.08
A40: r base | B40: 0.12 | C40: основная ставка
A41: r mid | B41: 0.15
A42: r high | B42: 0.21 | C42: Ключевая ставка ЦБ

Sheet ФОТ_B_v6
A1: Параметр | B1: Год 1 | C1: Год 2 | D1: Год 3 | E1: Год 4 | F1: Год 5 | G1: Год 6 | H1: Год 7 | I1: Год 8 | J1: Год 9 | K1: Год 10 | L1: ИТОГО
A2: Штат, чел. | B2: 25 | C2: 25 | D2: 32 | E2: 32 | F2: 32 | G2: 35 | H2: 35 | I2: 35 | J2: 35 | K2: 35
A3: Фикс./перем. | B3: 80/20 | C3: 60/40 | D3: 40/60 | E3: 40/60 | F3: 40/60 | G3: 40/60 | H3: 40/60 | I3: 40/60 | J3: 40/60 | K3: 40/60
A4: Перем. множ. | B4: ×0,25 | C4: ×0,67 | D4: ×1,50 | E4: ×1,50 | F4: ×1,50 | G4: ×1,50 | H4: ×1,50 | I4: ×1,50 | J4: ×1,50 | K4: ×1,50
A5: ФОТ баз. (100%), тыс. | B5: 107100 | C5: 155737 | D5: 302446 | E5: 329446 | F5: 358862 | G5: 423247 | H5: 461049 | I5: 502260 | J5: 547192 | K5: 596231 | L5: =SUM(B5:K5) -> 3783570
A6: ФОТ итог. (+30,2%), тыс. | B6: =ROUND(B5*(1+Параметры!$B$6),0) -> 139444 | C6: =ROUND(C5*(1+Параметры!$B$6),0) -> 202770 | D6: =ROUND(D5*(1+Параметры!$B$6),0) -> 393785 | E6: =ROUND(E5*(1+Параметры!$B$6),0) -> 428939 | F6: =ROUND(F5*(1+Параметры!$B$6),0) -> 467238 | G6: =ROUND(G5*(1+Параметры!$B$6),0) -> 551068 | H6: =ROUND(H5*(1+Параметры!$B$6),0) -> 600286 | I6: =ROUND(I5*(1+Параметры!$B$6),0) -> 653943 | ... K6: =ROUND(K5*(1+Параметры!$B$6),0) -> 776293 | L6: =SUM(B6:K6) -> 4926210
A7: OPEX, тыс. | B7: =Параметры!$B$8 -> 28200 | C7: =ROUND(B7*(1+Параметры!$B$7),0) -> 29610 | D7: =ROUND(C7*(1+Параметры!$B$7),0) -> 31091 | E7: =ROUND(D7*(1+Параметры!$B$7),0) -> 32646 | F7: =ROUND(E7*(1+Параметры!$B$7),0) -> 34278 | G7: =ROUND(F7*(1+Параметры!$B$7),0) -> 35992 | H7: =ROUND(G7*(1+Параметры!$B$7),0) -> 37792 | I7: =ROUND(H7*(1+Параметры!$B$7),0) -> 39682 | J7: =ROUND(I7*(1+Параметры!$B$7),0) -> 41666 | K7: =ROUND(J7*(1+Параметры!$B$7),0) -> 43749 | L7: =SUM(B7:K7) -> 354706
A8: ИТОГО затраты, тыс. | B8: =B6+B7 -> 167644 | C8: =C6+C7 -> 232380 | D8: =D6+D7 -> 424876 | E8: =E6+E7 -> 461585 | F8: =F6+F7 -> 501516 | G8: =G6+G7 -> 587060 | H8: =H6+H7 -> 638078 | I8: =I6+I7 -> 693625 | ... K8: =K6+K7 -> 820042 | L8: =SUM(B8:K8) -> 5280916
A9: Хедж (0% KPI), тыс. | B9: =ROUND(85680*(1+Параметры!$B$6),0)+B7 -> 139755 | C9: =ROUND(93419*(1+Параметры!$B$6),0)+C7 -> 151242 | D9: =ROUND(120929*(1+Параметры!$B$6),0)+D7 -> 188541 | E9: =ROUND(131816*(1+Параметры!$B$6),0)+E7 -> 204270 | F9: =ROUND(143685*(1+Параметры!$B$6),0)+F7 -> 221356 | G9: =ROUND(169426*(1+Параметры!$B$6),0)+G7 -> 256585 | H9: =ROUND(184705*(1+Параметры!$B$6),0)+H7 -> 278278 | I9: =ROUND(201400*(1+Параметры!$B$6),0)+I7 -> 301905 | J9: =ROUND(219528*(1+Параметры!$B$6),0)+J7 -> 327491 | K9: =ROUND(239254*(1+Параметры!$B$6),0)+K7 -> 355258 | L9: =SUM(B9:K9) -> 2424681
A10: Ср. комп./мес., тыс. | B10: =ROUND(B6/B2/12,0) -> 465 | C10: =ROUND(C6/C2/12,0) -> 676 | D10: =ROUND(D6/D2/12,0) -> 1025 | E10: =ROUND(E6/E2/12,0) -> 1117 | F10: =ROUND(F6/F2/12,0) -> 1217 | G10: =ROUND(G6/G2/12,0) -> 1312 | H10: =ROUND(H6/H2/12,0) -> 1429 | I10: =ROUND(I6/I2/12,0) -> 1557 | ... K10: =ROUND(K6/K2/12,0) -> 1848
A11: Налоги ООО (оценка), тыс. | B11: 8000 | C11: 11500 | D11: 19000 | E11: 22000 | F11: 25000 | G11: 30000 | H11: 33000 | I11: 36500 | J11: 28000 | K11: 39000 | L11: 252000
A12: Затраты с налогами, тыс. | B12: =B8+B11 -> 175644 | C12: =C8+C11 -> 243880 | D12: =D8+D11 -> 443876 | E12: =E8+E11 -> 483585 | F12: =F8+F11 -> 526516 | G12: =G8+G11 -> 617060 | H12: =H8+H11 -> 671078 | I12: =I8+I11 -> 730125 | ... L12: =L8+L11 -> 5532916

Sheet TCV_Детализация
A1: Параметр | B1: Год 1 | C1: Год 2 | D1: Год 3 | E1: Год 4 | F1: Год 5 | G1: Год 6 | H1: Год 7 | I1: Год 8 | J1: Год 9 | K1: Год 10 | L1: ИТОГО
A2: Росатом: стратег. развитие [Гр.А] | B2: 400 | C2: 650 | D2: 850 | E2: 950 | F2: 1050 | G2: 1133 | H2: 1194 | I2: 1256 | J2: 1317 | K2: 1350 | L2: =SUM(B2:K2) -> 10150
A3: Прирост НИОКР (частный) [Гр.Б] | B3: 200 | C3: 380 | D3: 520 | E3: 600 | F3: 680 | G3: 752 | H3: 809 | I3: 866 | J3: 923 | K3: 960 | L3: =SUM(B3:K3) -> 6690
A4: Инвестиции и гранты [Гр.А] | B4: 250 | C4: 500 | D4: 750 | E4: 900 | F4: 1050 | G4: 1234 | H4: 1354 | I4: 1422 | J4: 1540 | K4: 1600 | L4: =SUM(B4:K4) -> 10600
A5: Корпоративное ДПО [Гр.А] | B5: 120 | C5: 250 | D5: 380 | E5: 450 | F5: 520 | G5: 579 | H5: 628 | I5: 677 | J5: 726 | K5: 760 | L5: =SUM(B5:K5) -> 5090
A6: Лицензирование [Гр.Б] | B6: 80 | C6: 170 | D6: 250 | E6: 300 | F6: 350 | G6: 395 | H6: 433 | I6: 472 | J6: 510 | K6: 540 | L6: =SUM(B6:K6) -> 3500
A7: Корп. фандрайзинг [Гр.В] | B7: 50 | C7: 100 | D7: 150 | E7: 175 | F7: 200 | G7: 221 | H7: 241 | I7: 261 | J7: 282 | K7: 300 | L7: =SUM(B7:K7) -> 1980
A8: Спин-оффы [Гр.В] | B8: 0 | C8: 0 | D8: 0 | E8: 25 | F8: 50 | G8: 36 | H8: 41 | I8: 46 | J8: 52 | K8: 90 | L8: =SUM(B8:K8) -> 340
A9: ИТОГО TCV, млн | B9: =SUM(B2:B8) -> 1100 | C9: =SUM(C2:C8) -> 2050 | D9: =SUM(D2:D8) -> 2900 | E9: =SUM(E2:E8) -> 3400 | F9: =SUM(F2:F8) -> 3900 | G9: =SUM(G2:G8) -> 4350 | H9: =SUM(H2:H8) -> 4700 | I9: =SUM(I2:I8) -> 5000 | ... K9: =SUM(K2:K8) -> 5600 | L9: =SUM(B9:K9) -> 38350
A11: Группа А TCV (Росатом+ДПО+Гранты) | B11: =B2+B4+B5 -> 770 | C11: =C2+C4+C5 -> 1400 | D11: =D2+D4+D5 -> 1980 | E11: =E2+E4+E5 -> 2300 | F11: =F2+F4+F5 -> 2620 | G11: =G2+G4+G5 -> 2946 | H11: =H2+H4+H5 -> 3176 | I11: =I2+I4+I5 -> 3355 | ... K11: =K2+K4+K5 -> 3710 | L11: =SUM(B11:K11) -> 25840
A12: Группа Б TCV (НИОКР+Лиценз.) | B12: =B3+B6 -> 280 | C12: =C3+C6 -> 550 | D12: =D3+D6 -> 770 | E12: =E3+E6 -> 900 | F12: =F3+F6 -> 1030 | G12: =G3+G6 -> 1147 | H12: =H3+H6 -> 1242 | I12: =I3+I6 -> 1338 | ... K12: =K3+K6 -> 1500 | L12: =SUM(B12:K12) -> 10190
A13: Группа В TCV (Фандр.+Спин-оффы) | B13: =B7+B8 -> 50 | C13: =C7+C8 -> 100 | D13: =D7+D8 -> 150 | E13: =E7+E8 -> 200 | F13: =F7+F8 -> 250 | G13: =G7+G8 -> 257 | H13: =H7+H8 -> 282 | I13: =I7+I8 -> 307 | ... K13: =K7+K8 -> 390 | L13: =SUM(B13:K13) -> 2320
A15: Cash-in А (BASE) | B15: =ROUND(B11*Параметры!$B$21,0) -> 462 | C15: =ROUND(C11*Параметры!$B$21,0) -> 840 | D15: =ROUND(D11*Параметры!$B$21,0) -> 1188 | E15: =ROUND(E11*Параметры!$B$21,0) -> 1380 | F15: =ROUND(F11*Параметры!$B$21,0) -> 1572 | G15: =ROUND(G11*Параметры!$B$21,0) -> 1768 | H15: =ROUND(H11*Параметры!$B$21,0) -> 1906 | I15: =ROUND(I11*Параметры!$B$21,0) -> 2013 | ... K15: =ROUND(K11*Параметры!$B$21,0) -> 2226 | L15: =SUM(B15:K15) -> 15505
A16: Cash-in Б (BASE) | B16: =ROUND(B12*Параметры!$B$22,0) -> 126 | C16: =ROUND(C12*Параметры!$B$22,0) -> 248 | D16: =ROUND(D12*Параметры!$B$22,0) -> 347 | E16: =ROUND(E12*Параметры!$B$22,0) -> 405 | F16: =ROUND(F12*Параметры!$B$22,0) -> 464 | G16: =ROUND(G12*Параметры!$B$22,0) -> 516 | H16: =ROUND(H12*Параметры!$B$22,0) -> 559 | I16: =ROUND(I12*Параметры!$B$22,0) -> 602 | ... K16: =ROUND(K12*Параметры!$B$22,0) -> 675 | L16: =SUM(B16:K16) -> 4587
A17: Cash-in В (BASE) | B17: =ROUND(B13*Параметры!$B$23,0) -> 10 | C17: =ROUND(C13*Параметры!$B$23,0) -> 20 | D17: =ROUND(D13*Параметры!$B$23,0) -> 30 | E17: =ROUND(E13*Параметры!$B$23,0) -> 40 | F17: =ROUND(F13*Параметры!$B$23,0) -> 50 | G17: =ROUND(G13*Параметры!$B$23,0) -> 51 | H17: =ROUND(H13*Параметры!$B$23,0) -> 56 | I17: =ROUND(I13*Параметры!$B$23,0) -> 61 | ... K17: =ROUND(K13*Параметры!$B$23,0) -> 78 | L17: =SUM(B17:K17) -> 463
A18: ИТОГО Cash-in (BASE), млн | B18: =B15+B16+B17 -> 598 | C18: =C15+C16+C17 -> 1108 | D18: =D15+D16+D17 -> 1565 | E18: =E15+E16+E17 -> 1825 | F18: =F15+F16+F17 -> 2086 | G18: =G15+G16+G17 -> 2335 | H18: =H15+H16+H17 -> 2521 | I18: =I15+I16+I17 -> 2676 | ... K18: =K15+K16+K17 -> 2979 | L18: =SUM(B18:K18) -> 20555
A19: Ср.взв. ставка CI | B19: =IF(B9=0,0,B18/B9) -> 0.54363636 | C19: =IF(C9=0,0,C18/C9) -> 0.5404878 | D19: =IF(D9=0,0,D18/D9) -> 0.53965517 | E19: =IF(E9=0,0,E18/E9) -> 0.53676471 | F19: =IF(F9=0,0,F18/F9) -> 0.53487179 | G19: =IF(G9=0,0,G18/G9) -> 0.53678161 | H19: =IF(H9=0,0,H18/H9) -> 0.53638298 | I19: =IF(I9=0,0,I18/I9) -> 0.5352 | ... K19: =IF(K9=0,0,K18/K9) -> 0.53196429
A21: --- SENSITIVITY (75/50/25) ---
A22: Cash-in А (SENS) | B22: =ROUND(B11*Параметры!$B$26,0) -> 578 | C22: =ROUND(C11*Параметры!$B$26,0) -> 1050 | D22: =ROUND(D11*Параметры!$B$26,0) -> 1485 | E22: =ROUND(E11*Параметры!$B$26,0) -> 1725 | F22: =ROUND(F11*Параметры!$B$26,0) -> 1965 | G22: =ROUND(G11*Параметры!$B$26,0) -> 2210 | H22: =ROUND(H11*Параметры!$B$26,0) -> 2382 | I22: =ROUND(I11*Параметры!$B$26,0) -> 2516 | ... K22: =ROUND(K11*Параметры!$B$26,0) -> 2783 | L22: =SUM(B22:K22) -> 19381
A23: Cash-in Б (SENS) | B23: =ROUND(B12*Параметры!$B$27,0) -> 140 | C23: =ROUND(C12*Параметры!$B$27,0) -> 275 | D23: =ROUND(D12*Параметры!$B$27,0) -> 385 | E23: =ROUND(E12*Параметры!$B$27,0) -> 450 | F23: =ROUND(F12*Параметры!$B$27,0) -> 515 | G23: =ROUND(G12*Параметры!$B$27,0) -> 574 | H23: =ROUND(H12*Параметры!$B$27,0) -> 621 | I23: =ROUND(I12*Параметры!$B$27,0) -> 669 | ... K23: =ROUND(K12*Параметры!$B$27,0) -> 750 | L23: =SUM(B23:K23) -> 5096
A24: Cash-in В (SENS) | B24: =ROUND(B13*Параметры!$B$28,0) -> 13 | C24: =ROUND(C13*Параметры!$B$28,0) -> 25 | D24: =ROUND(D13*Параметры!$B$28,0) -> 38 | E24: =ROUND(E13*Параметры!$B$28,0) -> 50 | F24: =ROUND(F13*Параметры!$B$28,0) -> 63 | G24: =ROUND(G13*Параметры!$B$28,0) -> 64 | H24: =ROUND(H13*Параметры!$B$28,0) -> 71 | I24: =ROUND(I13*Параметры!$B$28,0) -> 77 | ... K24: =ROUND(K13*Параметры!$B$28,0) -> 98 | L24: =SUM(B24:K24) -> 583
A25: ИТОГО Cash-in (SENS), млн | B25: =B22+B23+B24 -> 731 | C25: =C22+C23+C24 -> 1350 | D25: =D22+D23+D24 -> 1908 | E25: =E22+E23+E24 -> 2225 | F25: =F22+F23+F24 -> 2543 | G25: =G22+G23+G24 -> 2848 | H25: =H22+H23+H24 -> 3074 | I25: =I22+I23+I24 -> 3262 | ... K25: =K22+K23+K24 -> 3631 | L25: =SUM(B25:K25) -> 25060
A26: Ср.взв. ставка SENS | B26: =IF(B9=0,0,B25/B9) -> 0.66454545 | C26: =IF(C9=0,0,C25/C9) -> 0.65853659 | D26: =IF(D9=0,0,D25/D9) -> 0.65793103 | E26: =IF(E9=0,0,E25/E9) -> 0.65441176 | F26: =IF(F9=0,0,F25/F9) -> 0.65205128 | G26: =IF(G9=0,0,G25/G9) -> 0.65471264 | H26: =IF(H9=0,0,H25/H9) -> 0.65404255 | I26: =IF(I9=0,0,I25/I9) -> 0.6524 | ... K26: =IF(K9=0,0,K25/K9) -> 0.64839286

Sheet TCV_Сценарии
A1: Параметр | B1: Год 1 | C1: Год 2 | D1: Год 3 | E1: Год 4 | F1: Год 5 | G1: Год 6 | H1: Год 7 | I1: Год 8 | J1: Год 9 | K1: Год 10 | L1: ИТОГО
A2: TCV базовый, млн | B2: =TCV_Детализация!B9 -> 1100 | C2: =TCV_Детализация!C9 -> 2050 | D2: =TCV_Детализация!D9 -> 2900 | E2: =TCV_Детализация!E9 -> 3400 | F2: =TCV_Детализация!F9 -> 3900 | G2: =TCV_Детализация!G9 -> 4350 | H2: =TCV_Детализация!H9 -> 4700 | I2: =TCV_Детализация!I9 -> 5000 | ... K2: =TCV_Детализация!K9 -> 5600 | L2: =SUM(B2:K2) -> 38350
A3: Cash-in (BASE А60/Б45/В20%), млн | B3: =TCV_Детализация!B18 -> 598 | C3: =TCV_Детализация!C18 -> 1108 | D3: =TCV_Детализация!D18 -> 1565 | E3: =TCV_Детализация!E18 -> 1825 | F3: =TCV_Детализация!F18 -> 2086 | G3: =TCV_Детализация!G18 -> 2335 | H3: =TCV_Детализация!H18 -> 2521 | I3: =TCV_Детализация!I18 -> 2676 | ... K3: =TCV_Детализация!K18 -> 2979 | L3: =SUM(B3:K3) -> 20555
A4: Затраты, тыс. | B4: =ФОТ_B_v6!B8 -> 167644 | C4: =ФОТ_B_v6!C8 -> 232380 | D4: =ФОТ_B_v6!D8 -> 424876 | E4: =ФОТ_B_v6!E8 -> 461585 | F4: =ФОТ_B_v6!F8 -> 501516 | G4: =ФОТ_B_v6!G8 -> 587060 | H4: =ФОТ_B_v6!H8 -> 638078 | I4: =ФОТ_B_v6!I8 -> 693625 | ... K4: =ФОТ_B_v6!K8 -> 820042 | L4: =SUM(B4:K4) -> 5280916
A5: ROI (TCV), % [=(TCV×1000−Затр)/Затр×100] | B5: =ROUND((B2*1000-B4)/B4*100,0) -> 556 | C5: =ROUND((C2*1000-C4)/C4*100,0) -> 782 | D5: =ROUND((D2*1000-D4)/D4*100,0) -> 583 | E5: =ROUND((E2*1000-E4)/E4*100,0) -> 637 | F5: =ROUND((F2*1000-F4)/F4*100,0) -> 678 | G5: =ROUND((G2*1000-G4)/G4*100,0) -> 641 | H5: =ROUND((H2*1000-H4)/H4*100,0) -> 637 | I5: =ROUND((I2*1000-I4)/I4*100,0) -> 621 | ... K5: =ROUND((K2*1000-K4)/K4*100,0) -> 583
A6: Мультипликатор (TCV) | B6: =ROUND(B2*1000/B4,1) -> 6.6 | C6: =ROUND(C2*1000/C4,1) -> 8.8 | D6: =ROUND(D2*1000/D4,1) -> 6.8 | E6: =ROUND(E2*1000/E4,1) -> 7.4 | F6: =ROUND(F2*1000/F4,1) -> 7.8 | G6: =ROUND(G2*1000/G4,1) -> 7.4 | H6: =ROUND(H2*1000/H4,1) -> 7.4 | I6: =ROUND(I2*1000/I4,1) -> 7.2 | ... K6: =ROUND(K2*1000/K4,1) -> 6.8
A7: Кумул. TCV, млрд | B7: =ROUND(B2/1000,1) -> 1.1 | C7: =ROUND(B7+C2/1000,1) -> 3.2 | D7: =ROUND(C7+D2/1000,1) -> 6.1 | E7: =ROUND(D7+E2/1000,1) -> 9.5 | F7: =ROUND(E7+F2/1000,1) -> 13.4 | G7: =ROUND(F7+G2/1000,1) -> 17.8 | H7: =ROUND(G7+H2/1000,1) -> 22.5 | I7: =ROUND(H7+I2/1000,1) -> 27.5 | J7: =ROUND(I7+J2/1000,1) -> 32.9 | K7: =ROUND(J7+K2/1000,1) -> 38.5
A8: Кумул. Cash-in, млрд | B8: =ROUND(B3/1000,1) -> 0.6 | C8: =ROUND(B8+C3/1000,1) -> 1.7 | D8: =ROUND(C8+D3/1000,1) -> 3.3 | E8: =ROUND(D8+E3/1000,1) -> 5.1 | F8: =ROUND(E8+F3/1000,1) -> 7.2 | G8: =ROUND(F8+G3/1000,1) -> 9.5 | H8: =ROUND(G8+H3/1000,1) -> 12 | I8: =ROUND(H8+I3/1000,1) -> 14.7 | J8: =ROUND(I8+J3/1000,1) -> 17.6 | K8: =ROUND(J8+K3/1000,1) -> 20.6
A9: --- Сценарии TCV ---
A10: Пессимист. TCV (×коэфф.), млн | B10: =ROUND(B2*Параметры!$B$31,0) -> 770 | C10: =ROUND(C2*Параметры!$B$31,0) -> 1435 | D10: =ROUND(D2*Параметры!$B$31,0) -> 2030 | E10: =ROUND(E2*Параметры!$B$31,0) -> 2380 | F10: =ROUND(F2*Параметры!$B$31,0) -> 2730 | G10: =ROUND(G2*Параметры!$B$31,0) -> 3045 | H10: =ROUND(H2*Параметры!$B$31,0) -> 3290 | I10: =ROUND(I2*Параметры!$B$31,0) -> 3500 | ... K10: =ROUND(K2*Параметры!$B$31,0) -> 3920 | L10: =SUM(B10:K10) -> 26845
A11: Оптимист. TCV (×коэфф.), млн | B11: =ROUND(B2*Параметры!$B$32,0) -> 1507 | C11: =ROUND(C2*Параметры!$B$32,0) -> 2809 | D11: =ROUND(D2*Параметры!$B$32,0) -> 3973 | E11: =ROUND(E2*Параметры!$B$32,0) -> 4658 | F11: =ROUND(F2*Параметры!$B$32,0) -> 5343 | G11: =ROUND(G2*Параметры!$B$32,0) -> 5960 | H11: =ROUND(H2*Параметры!$B$32,0) -> 6439 | I11: =ROUND(I2*Параметры!$B$32,0) -> 6850 | ... K11: =ROUND(K2*Параметры!$B$32,0) -> 7672 | L11: =SUM(B11:K11) -> 52541
A12: Санкц. стресс TCV (×коэфф.), млн | B12: =ROUND(B2*Параметры!$B$33,0) -> 935 | C12: =ROUND(C2*Параметры!$B$33,0) -> 1743 | D12: =ROUND(D2*Параметры!$B$33,0) -> 2465 | E12: =ROUND(E2*Параметры!$B$33,0) -> 2890 | F12: =ROUND(F2*Параметры!$B$33,0) -> 3315 | G12: =ROUND(G2*Параметры!$B$33,0) -> 3698 | H12: =ROUND(H2*Параметры!$B$33,0) -> 3995 | I12: =ROUND(I2*Параметры!$B$33,0) -> 4250 | ... K12: =ROUND(K2*Параметры!$B$33,0) -> 4760 | L12: =SUM(B12:K12) -> 32599
A14: --- NPV (Cash-in − Затраты) ---
A15: NPV (CI−Затр, r=8%), млрд | B15: =ROUND(((B3*1000-B4)/(1+Параметры!$B$39)^1+(C3*1000-C4)/(1+Параметры!$B$39)^2+(D3*1000-D4)/(1+Параметры!$B$39)^3+(E3*1000-E4)/(1+Параметры!$B$39)^4+(F3*1000-F4)/(1+Параметры!$B$39)^5+(G3*1000-G4)/(1+Параметры!$B$39)^6+(H3*1000-H4)/(1+Параметры!$B$39)^7+(I3*1000-I4)/(1+Параметры!$B$39)^8+(J3*1000-J4)/(1+Параметры!$B$39)^9+(K3*1000-K4)/(1+Параметры!$B$39)^10)/1000000,2) -> 9.46
A16: NPV (CI−Затр, r=12%), млрд | B16: =ROUND(((B3*1000-B4)/(1+Параметры!$B$40)^1+(C3*1000-C4)/(1+Параметры!$B$40)^2+(D3*1000-D4)/(1+Параметры!$B$40)^3+(E3*1000-E4)/(1+Параметры!$B$40)^4+(F3*1000-F4)/(1+Параметры!$B$40)^5+(G3*1000-G4)/(1+Параметры!$B$40)^6+(H3*1000-H4)/(1+Параметры!$B$40)^7+(I3*1000-I4)/(1+Параметры!$B$40)^8+(J3*1000-J4)/(1+Параметры!$B$40)^9+(K3*1000-K4)/(1+Параметры!$B$40)^10)/1000000,2) -> 7.65
A17: NPV (CI−Затр, r=15%), млрд | B17: =ROUND(((B3*1000-B4)/(1+Параметры!$B$41)^1+(C3*1000-C4)/(1+Параметры!$B$41)^2+(D3*1000-D4)/(1+Параметры!$B$41)^3+(E3*1000-E4)/(1+Параметры!$B$41)^4+(F3*1000-F4)/(1+Параметры!$B$41)^5+(G3*1000-G4)/(1+Параметры!$B$41)^6+(H3*1000-H4)/(1+Параметры!$B$41)^7+(I3*1000-I4)/(1+Параметры!$B$41)^8+(J3*1000-J4)/(1+Параметры!$B$41)^9+(K3*1000-K4)/(1+Параметры!$B$41)^10)/1000000,2) -> 6.6
A18: NPV (CI−Затр, r=21%), млрд | B18: =ROUND(((B3*1000-B4)/(1+Параметры!$B$42)^1+(C3*1000-C4)/(1+Параметры!$B$42)^2+(D3*1000-D4)/(1+Параметры!$B$42)^3+(E3*1000-E4)/(1+Параметры!$B$42)^4+(F3*1000-F4)/(1+Параметры!$B$42)^5+(G3*1000-G4)/(1+Параметры!$B$42)^6+(H3*1000-H4)/(1+Параметры!$B$42)^7+(I3*1000-I4)/(1+Параметры!$B$42)^8+(J3*1000-J4)/(1+Параметры!$B$42)^9+(K3*1000-K4)/(1+Параметры!$B$42)^10)/1000000,2) -> 5.03
A19: NPV (TCV−Затр, r=12%), млрд | B19: =ROUND(((B2*1000-B4)/(1+Параметры!$B$40)^1+(C2*1000-C4)/(1+Параметры!$B$40)^2+(D2*1000-D4)/(1+Параметры!$B$40)^3+(E2*1000-E4)/(1+Параметры!$B$40)^4+(F2*1000-F4)/(1+Параметры!$B$40)^5+(G2*1000-G4)/(1+Параметры!$B$40)^6+(H2*1000-H4)/(1+Параметры!$B$40)^7+(I2*1000-I4)/(1+Параметры!$B$40)^8+(J2*1000-J4)/(1+Параметры!$B$40)^9+(K2*1000-K4)/(1+Параметры!$B$40)^10)/1000000,2) -> 16.52
A21: --- Net New TCV ---
A22: Baseline, млн | B22: =Параметры!$B$36 -> 500 | C22: =Параметры!$B$36 -> 500 | D22: =Параметры!$B$36 -> 500 | E22: =Параметры!$B$36 -> 500 | F22: =Параметры!$B$36 -> 500 | G22: =Параметры!$B$36 -> 500 | H22: =Параметры!$B$36 -> 500 | I22: =Параметры!$B$36 -> 500 | ... K22: =Параметры!$B$36 -> 500
A23: Net New TCV, млн | B23: =B2-B22 -> 600 | C23: =C2-C22 -> 1550 | D23: =D2-D22 -> 2400 | E23: =E2-E22 -> 2900 | F23: =F2-F22 -> 3400 | G23: =G2-G22 -> 3850 | H23: =H2-H22 -> 4200 | I23: =I2-I22 -> 4500 | ... K23: =K2-K22 -> 5100 | L23: =SUM(B23:K23) -> 33350
A24: Мульт. Net New | B24: =IF(B23=0,0,ROUND(B23*1000/B4,1)) -> 3.6 | C24: =IF(C23=0,0,ROUND(C23*1000/C4,1)) -> 6.7 | D24: =IF(D23=0,0,ROUND(D23*1000/D4,1)) -> 5.6 | E24: =IF(E23=0,0,ROUND(E23*1000/E4,1)) -> 6.3 | F24: =IF(F23=0,0,ROUND(F23*1000/F4,1)) -> 6.8 | G24: =IF(G23=0,0,ROUND(G23*1000/G4,1)) -> 6.6 | H24: =IF(H23=0,0,ROUND(H23*1000/H4,1)) -> 6.6 | I24: =IF(I23=0,0,ROUND(I23*1000/I4,1)) -> 6.5 | ... K24: =IF(K23=0,0,ROUND(K23*1000/K4,1)) -> 6.2
A26: --- Кумулятивные метрики ---
A27: Кумул. ROI (TCV), % | B27: =ROUND((L2*1000-L4)/L4*100,0) -> 626
A28: Кумул. Мультипликатор (TCV) | B28: =ROUND(L2*1000/L4,1) -> 7.3
A29: Кумул. ROI (CI), % | B29: =ROUND((L3*1000-L4)/L4*100,0) -> 289
A30: Кумул. Мультипликатор (CI) | B30: =ROUND(L3*1000/L4,1) -> 3.9
A32: --- Справочно: с учётом налогов ООО (~252 млн) ---
A33: Затраты с налогами 10 лет, тыс. | B33: 5532916
A34: ROI (TCV, с налогами), % | B34: 593
A35: Мульт. (TCV, с налогами) | B35: 6.9
A36: NPV (CI, с налогами, r=12%), млрд | B36: 7.3

Sheet Sensitivity
A1: SENSITIVITY: Cash-in ставки
A3: Метрика | B3: BASE (60/45/20) | C3: ALT (75/50/25) | D3: Δ
A4: Ставки А/Б/В | B4: 60/45/20 | C4: 75/50/25 | D4: —
A5: Cash-in 10 лет, млрд | B5: =ROUND(TCV_Детализация!L18/1000,1) -> 20.6 | C5: =ROUND(TCV_Детализация!L25/1000,1) -> 25.1 | D5: =C5-B5 -> 4.5
A6: Cash-in Год 1, млн | B6: =TCV_Детализация!B18 -> 598 | C6: =TCV_Детализация!B25 -> 731 | D6: =C6-B6 -> 133
A7: Ср.взв. ставка Г1 | B7: =TCV_Детализация!B19 -> 0.54363636 | C7: =TCV_Детализация!B26 -> 0.66454545 | D7: =C7-B7 -> 0.12090909
A8: NPV (CI−Затр, r=12%), млрд | B8: =ROUND(((TCV_Детализация!B18*1000-ФОТ_B_v6!B8)/(1+Параметры!$B$40)^1+(TCV_Детализация!C18*1000-ФОТ_B_v6!C8)/(1+Параметры!$B$40)^2+(TCV_Детализация!D18*1000-ФОТ_B_v6!D8)/(1+Параметры!$B$40)^3+(TCV_Детализация!E18*1000-ФОТ_B_v6!E8)/(1+Параметры!$B$40)^4+(TCV_Детализация!F18*1000-ФОТ_B_v6!F8)/(1+Параметры!$B$40)^5+(TCV_Детализация!G18*1000-ФОТ_B_v6!G8)/(1+Параметры!$B$40)^6+(TCV_Детализация!H18*1000-ФОТ_B_v6!H8)/(1+Параметры!$B$40)^7+(TCV_Детализация!I18*1000-ФОТ_B_v6!I8)/(1+Параметры!$B$40)^8+(TCV_Детализация!J18*1000-ФОТ_B_v6!J8)/(1+Параметры!$B$40)^9+(TCV_Детализация!K18*1000-ФОТ_B_v6!K8)/(1+Параметры!$B$40)^10)/1000000,2) -> 7.65 | C8: =ROUND(((TCV_Детализация!B25*1000-ФОТ_B_v6!B8)/(1+Параметры!$B$40)^1+(TCV_Детализация!C25*1000-ФОТ_B_v6!C8)/(1+Параметры!$B$40)^2+(TCV_Детализация!D25*1000-ФОТ_B_v6!D8)/(1+Параметры!$B$40)^3+(TCV_Детализация!E25*1000-ФОТ_B_v6!E8)/(1+Параметры!$B$40)^4+(TCV_Детализация!F25*1000-ФОТ_B_v6!F8)/(1+Параметры!$B$40)^5+(TCV_Детализация!G25*1000-ФОТ_B_v6!G8)/(1+Параметры!$B$40)^6+(TCV_Детализация!H25*1000-ФОТ_B_v6!H8)/(1+Параметры!$B$40)^7+(TCV_Детализация!I25*1000-ФОТ_B_v6!I8)/(1+Параметры!$B$40)^8+(TCV_Детализация!J25*1000-ФОТ_B_v6!J8)/(1+Параметры!$B$40)^9+(TCV_Детализация!K25*1000-ФОТ_B_v6!K8)/(1+Параметры!$B$40)^10)/1000000,2) -> 9.9 | D8: =C8-B8 -> 2.25
A9: ROI кумул. (CI), % | B9: =ROUND((TCV_Детализация!L18*1000-ФОТ_B_v6!L8)/ФОТ_B_v6!L8*100,0) -> 289 | C9: =ROUND((TCV_Детализация!L25*1000-ФОТ_B_v6!L8)/ФОТ_B_v6!L8*100,0) -> 375 | D9: =C9-B9 -> 86
A10: Мульт. кумул. (CI) | B10: =ROUND(TCV_Детализация!L18*1000/ФОТ_B_v6!L8,1) -> 3.9 | C10: =ROUND(TCV_Детализация!L25*1000/ФОТ_B_v6!L8,1) -> 4.7 | D10: =C10-B10 -> 0.8

Sheet KPI_Структура
A1: KPI | B1: Вес | C1: Год 1 | D1: Год 2 | E1: Год 3 | F1: Год 5 | G1: Год 10
A2: Total Inflows (TCV+CI) | B2: 45% | C2: >150 млн | D2: >350 млн | E2: >600 млн | F2: >1 000 млн | G2: >2 000 млн
A3: Кол-во закрытых сделок | B3: 10% | C3: >20 | D3: >45 | E3: >70 | F3: >100 | G3: >160
A4: Средний размер (TCV) | B4: 10% | C4: >5 млн | D4: >7 млн | E4: >8,5 млн | F4: >10 млн | G4: >12,5 млн
A5: Объём привл. инвестиций | B5: 10% | C5: >50 млн | D5: >120 млн | E5: >200 млн | F5: >350 млн | G5: >600 млн
A6: ROI (cash-in/затраты) | B6: 5% | C6: >100% | D6: >200% | E6: >300% | F6: >450% | G6: >600%
A7: Retention (S+A) | B7: 8% | C7: — | D7: >80% | E7: >85% | F7: >90% | G7: >92%
A8: NPS партнёров | B8: 5% | C8: >50 | D8: >60 | E8: >65 | F8: >70 | G8: >75
A9: SLA (<2 раб. дн.) | B9: 5% | C9: >85% | D9: >90% | E9: >92% | F9: >95% | G9: >97%
A10: Стратег. партнёры (S+A) | B10: 2% | C10: >5 | D10: >12 | E10: >20 | F10: >35 | G10: >60

Sheet Перс_KPI_Матрица
A1: Должность | B1: Грейд | C1: Фикс./мес. Г.1 | D1: Ключевой KPI (вес) | E1: Цель Г.1 | F1: Цель Г.2 | G1: Цель Г.3 | H1: Цель Г.5 | I1: Блок
A2: Директор ЦПИКП | B2: G1 | C2: 667 | D2: Total Inflows (40%) | E2: >150 млн | F2: >350 млн | G2: >600 млн | H2: >1 000 млн | I2: Рук-во
A3: Первый зам. | B3: G2 | C3: 480 | D3: Inflows контр. (30%) | E3: >100 млн | F3: >250 млн | G3: >420 млн | H3: >700 млн | I3: Рук-во
A4: Зам. директора | B4: G2 | C4: 433 | D4: Inflows контр. (25%) | E4: >70 млн | F4: >180 млн | G4: >300 млн | H4: >500 млн | I4: Рук-во
A5: Рук. Блока 1 (Инвест.) | B5: G3 | C5: 320 | D5: Объём инвест. (35%) | E5: >50 млн | F5: >120 млн | G5: >200 млн | H5: >350 млн | I5: Блок 1
A6: Инвест. менеджер ×2 | B6: G4 | C6: 253 | D6: Персон. объём (40%) | E6: >15 млн | F6: >40 млн | G6: >70 млн | H6: >120 млн | I6: Блок 1
A7: Аналитик инвест. ×2 | B7: G5 | C7: 187 | D7: Паспорта (25%) | E7: >8 | F7: >14 | G7: >18 | H7: >22 | I7: Блок 1
A8: Рук. Блока 2 (Фронт) | B8: G3 | C8: 320 | D8: Объём средств (25%) | E8: >80 млн | F8: >180 млн | G8: >300 млн | H8: >450 млн | I8: Блок 2
A9: Менеджер заказов ×2 | B9: G4 | C9: 227 | D9: Обращения (20%) | E9: >80 | F9: >160 | G9: >240 | H9: >360 | I9: Блок 2
A10: Специалист ×2 | B10: G5 | C10: 167 | D10: Конверсия (20%) | E10: >12% | F10: >15% | G10: >18% | H10: >20% | I10: Блок 2
A11: Рук. Блока 3 (KAM) | B11: G3 | C11: 320 | D11: Объём KAM (35%) | E11: >100 млн | F11: >250 млн | G11: >400 млн | H11: >650 млн | I11: Блок 3
A12: Ст. KAM-менеджер ×3 | B12: G4 | C12: 280 | D12: Объём портфеля (40%) | E12: >25 млн | F12: >60 млн | G12: >100 млн | H12: >170 млн | I12: Блок 3
... A18: Юрист по сделкам/IP | B18: G4 | C18: 280 | D18: Контракты (15%) | E18: >30 | F18: >60 | G18: >90 | H18: >130 | I18: Блок 5

Sheet Дорожная_карта
A1: Период | B1: Действие | C1: KPI / результат | D1: Ответственный
A2: Мес. 1 | B2: Решение ректора. Рег. ООО. Назначение директора. | C2: ООО зарегистрировано | D2: Ректор
A3: Мес. 1-3 | B3: Волна 1: 6 чел. (директор, 1й зам, 4 рук. блоков) | C3: Укомплект. 24% | D3: Директор
A4: Мес. 3-6 | B4: Волна 2: +8 → 14 чел. (зам, KAM, инвест. менедж.) | C4: TCV >200 млн | D4: Директор
A5: Мес. 6-9 | B5: Волна 3: +11 → 25 чел. (полный штат Ф1) | C5: Pipeline >500 млн | D5: Директор
A6: Мес. 10-12 | B6: МИФИ Innovation Day. Первый целевой капитал. | C6: Cash-in >598 млн | D6: Директор
A7: Мес. 12 | B7: T1: Годовой отчёт ректору | C7: ROI оценка | D7: Ректор
A8: Мес. 13-18 | B8: Proof of Concept. Интеграция CRM+Эндаумент | C8: ROI(CI) >150% | D8: Директор
A9: Мес. 18 | B9: T2: Решение об интеграции | C9: T2 пройдена | D9: Набл. совет
A10: Мес. 19-24 | B10: Масштабирование pipeline. >100 партнёров | C10: Cash-in >1 108 млн | D10: Директор
A11: Мес. 24 | B11: T3: Решение ООО→Департамент | C11: T3 пройдена | D11: Учёный совет
A12: Год 3 Q1-Q2 | B12: Волна 4: +7 → 32 чел. KAM Росатом выделенный | C12: 32 чел. (100% Ф2) | D12: Директор
... A19: Год 9-10 | B19: Зрелая модель. >150 партнёров. >5 млрд TCV/год | C19: CI >3 360 млн | D19: Набл. совет

Sheet Changelog
A1: CHANGELOG: CPIKP_Calculations
A2: История изменений финансовой модели ЦПИКП
A4: Версия | B4: Дата | C4: Описание | D4: Ключевые изменения
A5: v1.0 | B5: Февр. 2026 | C5: Первоначальная модель | D5: Set 0: cash-in 60% flat. 5 листов, ~200 формул.
A6: v2.0 | B6: Февр. 2026 | C6: Калибровка cash-in | D6: Set A: 75/50/25 по группам. Добавлены Sensitivity, KPI, Дор. карта.
A7: v3.0 | B7: Март 2026 | C7: Финальная калибровка | D7: Set B: 60/45/20 (базовые ставки). OPEX: 22 500 → 28 200.
A8: v3.2 | B8: Март 2026 | C8: Формулы + Parameters | D8: Parameters sheet как single source of truth. 378 формул. Net New TCV.
A9: v3.3 | B9: Март 2026 | C9: Налоги ООО | D9: Добавлены строки налогов (~252 млн/10 лет). Справочные ROI/NPV с налогами.
A10: v3.4 | B10: Март 2026 | C10: Changelog + финализация | D10: Добавлен лист Changelog. Все правки аудита (48 замечаний) учтены.
A13: Детализация изменений v3.2 → v3.4
A15: Стадия | B15: ID замечания | C15: Лист | D15: Изменение | E15: БЫЛО | F15: СТАЛО
A16: Ст. 7 | B16: 5-ВЫС-8 | C16: ФОТ_B_v6 | D16: Добавлена строка «Налоги ООО (оценка)» | E16: — | F16: 8 000 → 39 000 тыс./год
A17: Ст. 7 | B17: 5-ВЫС-8 | C17: ФОТ_B_v6 | D17: Добавлена строка «Затраты с налогами» (формулы) | E17: — | F17: Формула: Затраты + Налоги
A18: Ст. 7 | B18: 5-ВЫС-8 | C18: TCV_Сценарии | D18: Справочно: ROI TCV с налогами | E18: — | F18: 593%
A19: Ст. 7 | B19: 5-ВЫС-8 | C19: TCV_Сценарии | D19: Справочно: Мульт. TCV с налогами | E19: — | F19: 6,9x
A20: Ст. 7 | B20: 5-ВЫС-8 | C20: TCV_Сценарии | D20: Справочно: NPV CI с налогами (r=12%) | E20: — | F20: 7,3 млрд
A21: v3.2 | B21: — | C21: Параметры | D21: OPEX Г1 = 28 200 (детализация) | E21: 22 500 | F21: 28 200
A22: v3.2 | B22: — | C22: Параметры | D22: Cash-in ставки BASE | E22: 60% flat | F22: А=60%, Б=45%, В=20%
A23: v3.2 | B23: — | C23: TCV_Сценарии | D23: Net New TCV (строки 21–24) | E23: — | F23: Baseline 500 + Net New
A24: v3.2 | B24: — | C24: TCV_Сценарии | D24: Кумулятивные метрики (строки 26–30) | E24: — | F24: ROI 626%, Мульт. 7,3x / 3,9x
A25: v3.2 | B25: — | C25: Sensitivity | D25: Сравнение BASE vs ALT ставок | E25: — | F25: BASE 60/45/20 vs ALT 75/50/25
A26: v3.4 | B26: — | C26: Changelog | D26: Добавлен лист Changelog | E26: — | F26: Настоящий лист
A29: Эталонные метрики (источник истины)
A31: Метрика | B31: Значение | C31: Лист / ячейка
A32: TCV 10 лет (базовый) | B32: 38 350 млн (~38,4 млрд) | C32: TCV_Сценарии!L2
A33: Cash-in 10 лет (BASE) | B33: 20 555 млн (~20,6 млрд) | C33: TCV_Сценарии!L3
A34: Совокупные затраты 10 лет | B34: 5 280 916 тыс. (~5,28 млрд) | C34: ФОТ_B_v6!L8 / TCV_Сценарии!L4
A35: Налоги ООО 10 лет | B35: ~252 000 тыс. | C35: ФОТ_B_v6!L11
A36: Затраты с налогами | B36: ~5 533 000 тыс. | C36: ФОТ_B_v6!L12
A37: NPV (CI−Затр, r=12%) | B37: 7,65–7,66 млрд | C37: TCV_Сценарии!B16
A38: NPV (TCV−Затр, r=12%) | B38: 16,52 млрд | C38: TCV_Сценарии!B19
A39: ROI кумул. (TCV) | B39: 626% | C39: TCV_Сценарии!B27
A40: ROI кумул. (CI) | B40: 289% | C40: TCV_Сценарии!B29
A41: Мульт. кумул. (TCV) | B41: 7,3x | C41: TCV_Сценарии!B28
A42: Мульт. кумул. (CI) | B42: 3,9x | C42: TCV_Сценарии!B30
... A47: Break-even | B47: 15–20 мес. | C47: Расчётный
